README.rst
setup.py
./sqlaqb/__init__.py
./sqlaqb/langhelpers.py
./sqlaqb/tests/__init__.py
./sqlaqb/tests/test_it_class.py
./sqlaqb/tests/test_it_directly.py
sqlaqb.egg-info/PKG-INFO
sqlaqb.egg-info/SOURCES.txt
sqlaqb.egg-info/dependency_links.txt
sqlaqb.egg-info/entry_points.txt
sqlaqb.egg-info/requires.txt
sqlaqb.egg-info/top_level.txt