Metadata-Version: 1.1
Name: sqlaqb
Version: 0.0.1
Summary: utility for portable model definition of sqlalchemy models
Home-page: UNKNOWN
Author: podhmo
Author-email: UNKNOWN
License: UNKNOWN
Platform: UNKNOWN
Classifier: Programming Language :: Python
Classifier: Programming Language :: Python :: 3
